{
    "questionSet": [
      {
        "question": "Mrs. Meena gave drinks to the people coming to the fair. She gave 75 drinks. There were 12 people who did not get drinks. How many peoples were in the fair?",
        "options": [
          { "value": "80" },
          { "value": "87" },
          { "value": "90" },
          { "value": "100" }
        ],
        "rightAnswer": "87",
        "userAnswer": ""
      },
      {
        "question": "John sold 76 hot dogs with mustard. He sold 64 hot dogs with redish. How many hot dogs were sold by John altogether?",
        "options": [
          { "value": "120" },
          { "value": "140" },
          { "value": "160" },
          { "value": "98 " }
        ],
        "rightAnswer": "140",
        "userAnswer": ""
      },
      {
        "question": "Mrs. Khurana's biggest tomato was 20 pounds. Mrs. Malik's biggest tomato was 14 pounds. Mrs. Sharma's biggest tomato's weight was 3 pounds lighter than Mrs. Khurana's. Whose tomato was lightest?",
        "options": [
          { "value": "Mrs. Khurana" },
          { "value": "Mrs. Malik" },
          { "value": "Mrs. Sharma" },
          { "value": "None of these" }
        ],
        "rightAnswer": "Mrs. Malik",
        "userAnswer": ""
      },
      {
        "question": "Twelve children are on the ride. Five more get on and two get off. How many children are now on the ride?",
        "options": [
          { "value": "15" },
          { "value": "20" },
          { "value": "10" },
          { "value": "12" }
        ],
        "rightAnswer": "15",
        "userAnswer": ""
      },
      {
        "question": "Cost of Drinks in the fair is ` 1.00 each. How many drinks can Mr. John buy for ` 10/-?",
        "options": [
          { "value": "5" },
          { "value": "10" },
          { "value": "8" },
          { "value": "15" }
        ],
        "rightAnswer": "10",
        "userAnswer": ""
      }
    ]
  }
  